soundstream/__init__.py
soundstream/decoder.py
soundstream/encoder.py
soundstream/soundstream.py
soundstream/units.py
soundstream-0.0.1.dist-info/LICENSE
soundstream-0.0.1.dist-info/METADATA
soundstream-0.0.1.dist-info/WHEEL
soundstream-0.0.1.dist-info/RECORD
