Metadata-Version: 2.1
Name: soundstream
Version: 0.0.1
Summary: Implementation of SoundStream, an end-to-end neural audio codec
License: MIT
Author: Hayden Shively
Requires-Python: >=3.10,<4.0
Classifier: License :: OSI Approved :: MIT License
Classifier: Programming Language :: Python :: 3
Classifier: Programming Language :: Python :: 3.10
Classifier: Programming Language :: Python :: 3.11
Requires-Dist: huggingface-hub (>=0.15.1,<0.16.0)
Requires-Dist: numpy (>=1.24.3,<2.0.0)
Requires-Dist: torch (>=2.0.1,<3.0.0)
Requires-Dist: torchaudio (>=2.0.2,<3.0.0)
Requires-Dist: vector-quantize-pytorch (>=1.6.11,<2.0.0)
